mcp_operator/__init__.py
mcp_operator/mcp_operator.py
mseep_kube_mcp_operator-0.1.0.dist-info/licenses/LICENSE
sidecar/__init__.py
sidecar/main.py
mseep_kube_mcp_operator-0.1.0.dist-info/METADATA
mseep_kube_mcp_operator-0.1.0.dist-info/WHEEL
mseep_kube_mcp_operator-0.1.0.dist-info/top_level.txt
mseep_kube_mcp_operator-0.1.0.dist-info/RECORD
